oyna/__init__.py
oyna/bubble_shooter/__init__.py
oyna/bubble_shooter/grid_base.py
oyna/checkers/__init__.py
oyna/checkers/grid_base.py
oyna/chimp/__init__.py
oyna/chimp/grid_base.py
oyna/chutes_and_ladders/__init__.py
oyna/chutes_and_ladders/grid_base.py
oyna/dino/__init__.py
oyna/dino/grid_base.py
oyna/falling_tower/__init__.py
oyna/falling_tower/grid_base.py
oyna/find_difference/__init__.py
oyna/find_difference/grid_base.py
oyna/flappy_bird/__init__.py
oyna/flappy_bird/grid_base.py
oyna/matching/__init__.py
oyna/matching/grid_base.py
oyna/maze/__init__.py
oyna/maze/grid_base.py
oyna/minesweeper/__init__.py
oyna/minesweeper/grid_base.py
oyna/reverse_slide_puzzle/__init__.py
oyna/reverse_slide_puzzle/grid_base.py
oyna/reversi/__init__.py
oyna/reversi/grid_base.py
oyna/shoot_colors/__init__.py
oyna/shoot_colors/grid_base.py
oyna/snake/__init__.py
oyna/snake/grid_base.py
oyna/sudoku/__init__.py
oyna/sudoku/grid_base.py
oyna/supermario_pixel/__init__.py
oyna/supermario_pixel/grid_base.py
oyna/tetris/__init__.py
oyna/tetris/grid_base.py
oyna/tik_tok_toe/__init__.py
oyna/tik_tok_toe/grid_base.py
oyna/twenty_forty_eight_2048/__init__.py
oyna/twenty_forty_eight_2048/grid_base.py
oyna/ufo_explosion/__init__.py
oyna/ufo_explosion/grid_base.py
oyna-1.1.1.dist-info/licenses/LICENSE
oyna-1.1.1.dist-info/METADATA
oyna-1.1.1.dist-info/WHEEL
oyna-1.1.1.dist-info/entry_points.txt
oyna-1.1.1.dist-info/top_level.txt
oyna-1.1.1.dist-info/RECORD
