Metadata-Version: 2.4
Name: oyna
Version: 1.1.1
Summary: The Python Games Library for Playing and Learning.
Author-email: "Kamyar M.G." <kmgurmia@gmail.com>
Maintainer-email: "Kamyar M.G." <kmgurmia@gmail.com>
License: MIT License
Project-URL: Homepage, https://github.com/kamyarmg/oyna
Project-URL: Repository, https://github.com/kamyarmg/oyna
Project-URL: Issues, https://github.com/kamyarmg/oyna/issues
Project-URL: Changelog, https://github.com/kamyarmg/oyna/blob/master/CHANGES.rst
Keywords: games,python,alghorithms,data structures,fun,OYNA
Classifier: Development Status :: 1 - Planning
Classifier: Intended Audience :: Developers
Classifier: Topic :: Software Development :: Build Tools
Classifier: Topic :: File Formats :: JSON
Classifier: License :: OSI Approved :: MIT License
Classifier: Programming Language :: Python :: 3
Classifier: Programming Language :: Python :: 3.10
Classifier: Programming Language :: Python :: 3.11
Classifier: Programming Language :: Python :: 3.12
Classifier: Programming Language :: Python :: 3.13
Requires-Python: >=3.10
License-File: LICENSE
Requires-Dist: pynput>=1.7.7
Dynamic: license-file
